neptoon/__init__.py
neptoon/calibration/__init__.py
neptoon/calibration/station_calibration.py
neptoon/cli/__init__.py
neptoon/cli/cli.py
neptoon/cli/launcher.py
neptoon/columns/__init__.py
neptoon/columns/column_information.py
neptoon/config/__init__.py
neptoon/config/configuration_input.py
neptoon/config/global_configuration.py
neptoon/corrections/__init__.py
neptoon/corrections/assets/footprint_radius.csv
neptoon/corrections/factory/__init__.py
neptoon/corrections/factory/build_corrections.py
neptoon/corrections/factory/correction_classes.py
neptoon/corrections/theory/__init__.py
neptoon/corrections/theory/above_ground_biomass_corrections.py
neptoon/corrections/theory/air_humidity_corrections.py
neptoon/corrections/theory/calibration_functions.py
neptoon/corrections/theory/incoming_intensity_corrections.py
neptoon/corrections/theory/neutrons_to_soil_moisture.py
neptoon/corrections/theory/pressure_corrections.py
neptoon/data_audit/__init__.py
neptoon/data_audit/data_audit.py
neptoon/data_prep/__init__.py
neptoon/data_prep/conversions.py
neptoon/data_prep/cutoff_rigidity_lookup.py
neptoon/data_prep/smoothing.py
neptoon/data_prep/timestamp_alignment.py
neptoon/data_prep/assets/RC_2020.csv
neptoon/external/__init__.py
neptoon/external/nmdb_data_collection.py
neptoon/hub/__init__.py
neptoon/hub/crns_data_hub.py
neptoon/interface/__init__.py
neptoon/interface/gui-calibration.py
neptoon/interface/gui-configuration.py
neptoon/interface/gui-export.py
neptoon/interface/gui-neutron_corrections.py
neptoon/interface/gui-read_data.py
neptoon/interface/gui-run_all.py
neptoon/interface/gui-site_information.py
neptoon/interface/gui-water.py
neptoon/interface/gui.py
neptoon/interface/neptoon_gui_utils.py
neptoon/interface/.streamlit/config.toml
neptoon/interface/assets/UFZ_Logo_abbr.png
neptoon/interface/assets/neptoon-affils.png
neptoon/interface/assets/neptoon-affils.svg
neptoon/interface/assets/neptoon-logo-ball.svg
neptoon/interface/assets/neptoon-logo.svg
neptoon-0.13.7.dist-info/METADATA
neptoon-0.13.7.dist-info/WHEEL
neptoon-0.13.7.dist-info/entry_points.txt
neptoon-0.13.7.dist-info/licenses/LICENSE
neptoon-0.13.7.dist-info/RECORD
