Metadata-Version: 2.4
Name: neptoon
Version: 0.13.7
Summary: The neptoon package makes CRNS processing and research simple.
Project-URL: Homepage, https://www.neptoon.org
Project-URL: Repository, https://codebase.helmholtz.cloud/cosmos/neptoon
Project-URL: Documentation, https://www.neptoon.org
Author-email: Daniel Power <dpower-rse@pm.me>, Martin Schroen <martin.schroen@ufz.de>
License-Expression: MIT
License-File: LICENSE
Keywords: CRNS,Cosmic Ray Neutron Sensors,Cosmic Rays,crns,soil,soil moisture
Requires-Python: >=3.10
Requires-Dist: figurex>=0.2.15
Requires-Dist: magazine>=0.4.0
Requires-Dist: numpy>=2.0
Requires-Dist: pandas>=2.2.0
Requires-Dist: pandera>0.24
Requires-Dist: platformdirs>=4.2.0
Requires-Dist: pyaml>=23.12.0
Requires-Dist: pyarrow>=18.0.0
Requires-Dist: pydantic>=2.6.1
Requires-Dist: pytest>=8.0.0
Requires-Dist: python-dateutil>=2.8.2
Requires-Dist: pyyaml>=6.0.1
Requires-Dist: requests>=2.31.0
Requires-Dist: saqc>=2.7.0
Requires-Dist: seaborn>=0.13.2
Requires-Dist: typer>=0.15.2
Requires-Dist: urllib3>=2.2.0
Provides-Extra: dev
Requires-Dist: black>=24.1.1; extra == 'dev'
Requires-Dist: pytest-cov>=6.2.1; extra == 'dev'
Provides-Extra: gui
Requires-Dist: plotly>=6.0.0; extra == 'gui'
Requires-Dist: streamlit>=1.31.0; extra == 'gui'
Requires-Dist: typer>=0.15.1; extra == 'gui'
